fflib/__init__.py
fflib/enums.py
fflib/interfaces/__init__.py
fflib/interfaces/iff.py
fflib/interfaces/iff_recurrent_layer.py
fflib/interfaces/iffprobe.py
fflib/nn/__init__.py
fflib/nn/ff_linear.py
fflib/nn/ff_net.py
fflib/nn/ff_recurrent_layer.py
fflib/nn/ff_rnn.py
fflib/nn/ffc.py
fflib/probes/__init__.py
fflib/probes/identity.py
fflib/probes/one_hot.py
fflib/py.typed
fflib/utils/__init__.py
fflib/utils/bp_suite.py
fflib/utils/data/__init__.py
fflib/utils/data/dataprocessor.py
fflib/utils/data/mnist.py
fflib/utils/ff_logger.py
fflib/utils/ff_suite.py
fflib/utils/ffc_suite.py
fflib/utils/ffrnn_suite.py
fflib/utils/iff_suite.py
fflib/utils/maths.py
fflib-0.3.0.dist-info/METADATA
fflib-0.3.0.dist-info/WHEEL
fflib-0.3.0.dist-info/RECORD
