Metadata-Version: 2.3
Name: fflib
Version: 0.3.0
Summary: PyTorch-based library for the Forward-Forward algorithm
License: MIT
Author: Mitko Nikov
Author-email: mitkonikov01@gmail.com
Requires-Python: >=3.10
Classifier: License :: OSI Approved :: MIT License
Classifier: Programming Language :: Python :: 3
Classifier: Programming Language :: Python :: 3.10
Classifier: Programming Language :: Python :: 3.11
Classifier: Programming Language :: Python :: 3.12
Classifier: Programming Language :: Python :: 3.13
Classifier: Topic :: Scientific/Engineering :: Artificial Intelligence
Classifier: Topic :: Software Development :: Libraries :: Python Modules
Requires-Dist: torch (>=2.6.0,<3.0.0)
Requires-Dist: torchvision (>=0.21.0,<0.22.0)
Requires-Dist: tqdm (>=4.67.1,<5.0.0)
Project-URL: Bug Tracker, https://github.com/mitkonikov/ff/issues
Project-URL: Documentation, https://github.com/mitkonikov/ff
Project-URL: Homepage, https://github.com/mitkonikov/ff
Project-URL: Repository, https://github.com/mitkonikov/ff
